openaiwrapper/__init__.py
openaiwrapper/api_client.py
openaiwrapper/assistants.py
openaiwrapper/config.py
openaiwrapper/decorators.py
openaiwrapper/error_logging.py
openaiwrapper/exceptions.py
openaiwrapper/files.py
openaiwrapper/logging_config.py
openaiwrapper/main.py
openaiwrapper/messages.py
openaiwrapper/profiles.py
openaiwrapper/runs.py
openaiwrapper/threads.py
openaiwrapper/utils.py
openaiwrapper/vector_store_manager.py
openaiwrapper/profiles/coreteam_brie.json
openaiwrapper/profiles/coreteam_britt.json
openaiwrapper/profiles/coreteam_derek.json
openaiwrapper/profiles/coreteam_max.json
openaiwrapper/profiles/coreteam_nate.json
openaiwrapper/profiles/coreteam_riley.json
openaiwrapper/profiles/example_non_coreteam_profile.json
openaiwrapper/profiles/math_tutor.json
orchestrator/__init__.py
orchestrator/task_orchestrator.py
orchestrator/utils.py
tests/__init__.py
tests/test_main.py
tests/test_math_tutor.py
tests/test_send_msg_assistant.py
tests/test_send_msg_coreteam.py
botwrap-0.1.9.dist-info/METADATA
botwrap-0.1.9.dist-info/WHEEL
botwrap-0.1.9.dist-info/entry_points.txt
botwrap-0.1.9.dist-info/top_level.txt
botwrap-0.1.9.dist-info/RECORD
